README.md
flask_tus_cont.py
setup.py
Flask_Tus_Cont.egg-info/PKG-INFO
Flask_Tus_Cont.egg-info/SOURCES.txt
Flask_Tus_Cont.egg-info/dependency_links.txt
Flask_Tus_Cont.egg-info/not-zip-safe
Flask_Tus_Cont.egg-info/requires.txt
Flask_Tus_Cont.egg-info/top_level.txt