Metadata-Version: 2.1
Name: Flask-Tus-Cont
Version: 1.3.1
Summary: TUS protocol implementation
Home-page: https://github.com/gnubyte/Flask-Tus
Author: Patrick Hastings
Author-email: phastings@openmobo.com
License: MIT
Platform: any
Classifier: Environment :: Web Environment
Classifier: Intended Audience :: Developers
Classifier: License :: OSI Approved :: MIT License
Classifier: Operating System :: OS Independent
Classifier: Programming Language :: Python
Classifier: Topic :: Software Development :: Libraries :: Python Modules
